{
    "paths": {
        "ab+nwojzZO7ZHehoCJByEq": [
            "GameJsonCfg",
            "cc.JsonAsset"
        ],
        "bdawJ4SIpGdZXEnMj29bP9": [
            "data",
            "cc.JsonAsset"
        ]
    },
    "uuids": [
        "ab+nwojzZO7ZHehoCJByEq",
        "bdawJ4SIpGdZXEnMj29bP9"
    ],
    "scenes": {},
    "redirect": [],
    "deps": [],
    "packs": {},
    "name": "pbt_configs",
    "importBase": "import",
    "nativeBase": "native",
    "debug": true,
    "isZip": false,
    "encrypted": false,
    "versions": {
        "import": [
            "ab+nwojzZO7ZHehoCJByEq",
            "806dc",
            "bdawJ4SIpGdZXEnMj29bP9",
            "f38bd"
        ],
        "native": []
    }
}