{"paths":{"0":["js_b/tx_4",1],"1":["js/js_17",1],"2":["enemys/enemy_3",1],"3":["js_b/tx_15",1],"4":["js_b/tx_11",1],"5":["js/js_13",1],"6":["backs/cj_02",1],"7":["enemys/enemy_2",1],"8":["bubbles/yz_BUFF_09",1],"9":["bubbles/yz_BUFF_01",1],"10":["js/js_14",1],"11":["js_b/tx_12",1],"12":["js_b/tx_7",1],"13":["js_b/tx_3",1],"14":["js_b/tx_13",1],"15":["js_b/tx_9",1],"16":["js/js_10",1],"17":["bubbles/yz_BUFF_02",1],"18":["js/js_11",1],"19":["js/js_7",1],"20":["enemys/enemy_8",1],"21":["js/js_6",1],"22":["bubbles/yz_BUFF_05",1],"23":["enemys/enemy_6",1],"24":["enemys/enemy_4",1],"25":["js_b/tx_17",1],"26":["js/js_3",1],"27":["js/js_12",1],"28":["js/js_9",1],"29":["js_b/tx_2",1],"30":["js_b/tx_18",1],"31":["js_b/tx_5",1],"32":["js/js_8",1],"33":["js/js_15",1],"34":["enemys/enemy_7",1],"35":["js_b/tx_1",1],"36":["js_b/tx_6",1],"37":["enemys/enemy_5",1],"38":["js/js_18",1],"39":["js/js_5",1],"40":["enemys/enemy_1",1],"41":["backs/cj_03",1],"42":["backs/cj_01",1],"43":["js_b/tx_10",1],"44":["js_b/tx_14",1],"45":["js_b/tx_8",1],"46":["js/js_16",1],"47":["js/js_1",1],"48":["enemys/enemy_9",1],"49":["js/js_2",1],"50":["js_b/tx_16",1],"51":["js/js_4",1],"52":["bubbles/yz_BUFF_09",0,1],"53":["enemys/enemy_6",0,1],"54":["js/js_1",2],"55":["js_b/tx_1",0,1],"56":["js_b/tx_13",0,1],"57":["backs/cj_01",0,1],"58":["js_b/tx_3",0,1],"59":["js_b/tx_7",0,1],"60":["js/js_14",0,1],"61":["js/js_17",0,1],"62":["js/js_13",0,1],"63":["bubbles/yz_BUFF_05",0,1],"64":["js/js_11",0,1],"65":["backs/cj_02",0,1],"66":["js/js_5",0,1],"67":["bubbles/yz_BUFF_01",2],"68":["js/js_16",0,1],"69":["js_b/tx_11",0,1],"70":["js_b/tx_6",0,1],"71":["js_b/tx_18",0,1],"72":["enemys/enemy_4",0,1],"73":["js/js_6",0,1],"74":["js_b/tx_12",0,1],"75":["js/js_10",0,1],"76":["js_b/tx_15",0,1],"77":["js/js_3",0,1],"78":["js_b/tx_2",0,1],"79":["js/js_8",0,1],"80":["js_b/tx_17",0,1],"81":["js/js_4",0,1],"82":["enemys/enemy_2",0,1],"83":["enemys/enemy_9",0,1],"84":["enemys/enemy_7",0,1],"85":["enemys/enemy_5",0,1],"86":["js/js_7",0,1],"87":["enemys/enemy_1",2],"88":["js_b/tx_16",0,1],"89":["js_b/tx_5",0,1],"90":["enemys/enemy_8",0,1],"91":["js/js_15",0,1],"92":["js/js_9",0,1],"93":["js_b/tx_9",0,1],"94":["backs/cj_03",0,1],"95":["enemys/enemy_3",0,1],"96":["bubbles/yz_BUFF_02",0,1],"97":["js_b/tx_14",0,1],"98":["js/js_2",0,1],"99":["js_b/tx_8",0,1],"100":["js_b/tx_4",0,1],"101":["js_b/tx_10",0,1],"102":["js/js_18",0,1],"103":["js/js_12",0,1]},"types":["cc.SpriteFrame","cc.Texture2D","cc.SpriteAtlas"],"uuids":["0aQJ2veZ1CTLwGBnltj0hG","0am0cGc/NCb5udXx2WEOZX","0cXoSuUuNL8Y8p0QOfSOM5","0esQZIRNlFXJgnpfRvFuj8","15yLl3dnlAAo+XqXzs1MdR","16GjPbNDtAFYH+vpV4pFMG","1d9GT7FOtHGqwDz/GwA+FP","21/9EBrhFNNIkwmPP9nO51","222dqes7JN1q9vFm9YyklH","23FBLLA3pKo4rNRyouZygI","23qjb/0OJBAovw1GQXMjVl","28lcNGSWZDQZsGrxWJtVjG","28u2WZ4etGuJPSQ0MTj8wB","30VfXUyQlPT4ww42GN16F9","32DOf0KThIpLGEUAmi55Wj","3f8sKOCppFGZyQdJLKBOiZ","41nWKdGzlGqLEqbEL+XZc5","45zUAOmrlGzoD1P6Ny3gol","46tss8bq1BrYl7m3ntWGP6","52Mzw6bhVGSahsCju6Jhjf","54WDMDte9IrZgQGWXlkZYF","57sztR8jtO7ql6MT+2D4/W","571xTisCFAgbi2dAnwpfew","58crMgRtVFhKHVrZrz8gSX","65IKyspcxHVqvDp5mtGEBN","6cPtnzw6FH2o8KZR/q+nKE","70IyHI1QVBY5FBebcAqosJ","74I3+61sFGkIOhvlT56Z8d","75q1fEgzZHC6KQUZPdcp6J","76UU+hdEtJH7YMjENK/MiW","76WGhYITRMd6itEi6mSWWh","815cwUTQtFHIGIE/XG7jer","89gR/AJPtM/rydi8InaSF8","98Bg768HJGpZYt1FxWk1tC","9bqlP1an5FSq4uHGw7sFbL","9dSYDm3vNJsqSPeiPJNSQi","9fYlQPGC9KLY3Kv9+rteyD","9f7YEd+PRFsq6wekBaa0bg","aaJZq29L5NPIBUlpdJu1BS","abip30dV1PRa/ceOCoPdkq","ad92F7WtxH+p2R0G0QziC4","b6WvpL+IJKs6gb8VgDCPuV","b91Ud/KpVNpbcLuysHAzM+","bcv4ByjbJJI7TcPcZRu8St","c0etfJWkZDgLtNAF0W44Zt","cckhErCA9GE4RMbp78l6c9","cectZ2s7BNAYgDqirmIFRO","d9esVoM5dGZ7uKVuomFH4K","ddYkrcR3ND3oVup2cZtrgI","e6E4rDFRZNfZmq883wQGhb","e6bSWlxB5Hh4c0sxYm3QJE","fayO1k9s1PF6iiDXMh6Ky0","032UwlCENG75RHKQgqzqrg","05ZWH0aKZCtqKDeU+EJNzO","10CZH3svpOYK3a1OPlGr3S","19o/tsDO9IZara4HhQe+RT","1bQyyJenhHR7tme6YHO103","20fAyz2BJPd4Erzia21zyG","34lou3UgRAVZzzRaWjQVSe","34sc4Hk5xHEINPVwe3Ffa0","38bgyhUrJF+IA493w+eMlD","3eGK9MkcBMyI1uTd4GxXaz","3eW9JO0RNH95ZrHq4MGLXC","4b4DDkL6lOprDpBTgJHFNr","4cp4ANpvlJiYiRinAwOGLQ","4dw1tAmTlHH56Eno25zAiA","51cwtnlzRIKYBBTUd089g2","557+ms+Q1BNLbLVmOj5sDH","5eiRFHz0lOILo7EYp50GE9","66iObrZxBFX6aHWN3jWhWJ","6daSr0hAFNyI0yGUOHoCKU","76AIWhcUtPF7BEr3WM+gTB","7a0RdZ0p9O6ZrsFPc28gBW","7cPQSXoF5My5R5sPNKrL3F","7dWaECT7JMYabvHLQpZUFs","7dqhJQLJhE6q4AE5t9JmpD","7dyPhlYCpN9roHRkiPhC34","8aQ/Hr5sdE94i68SSHZ7vr","8c5p6eFjNJHa9gQxx84zOV","90rc4Dc4NIa4xBI1MNVw3k","938qYc8DlKj6qkkWSROmJO","961gD/Hg5Jg7eOo3idaDdl","99Buh4xIBDupqGo8cNgUAZ","a5NYz8ZQdF5qKb5qUtr6CS","b3A/giI1hLsbbb/BLbnu/r","b3Z5DbMcxBiL1+CSJQrpRJ","bbQjVMjK9Ea421TTFiBJK6","bdog9bG9RIZpvcZ2DKTjI7","c5QP0NXb9P2aB1x80pkC0e","cd2mMJ5mtLQJV9PmEEhALS","cfLmfdye1F0pi20zee4Clv","d0aD0jY9tCX6yBhQ7yA66M","d1NErTBxNPq5VtPB2HGIz4","d5mdYQDVxDB6pCNtgVEJmE","d8s7LNFSRLYLjoZNp7d+M6","d9BO5e2wdAxqQp/i7ABBjR","dbcjbSVZRE9aZ8lT9QjV2N","e0uvlm/pFDjKh/3f0cNfH/","e8EAWQ/mBOXIjMBw0BHlwc","e8tRuTVmNG37lSiVKyWk3W","f5BGk0pyBLwa+FYn2IDxgC","f92rlJ1MdDL6Q7+pDgrNIl","feuRrb9/xID7n4Zozmc7Uu","ffDmqZOEJFwYUHZagYYqYj","08oa5O/hdP8Y0uoX5E48fY","1dQZBRCVpMJ5fAqp4EKLaa","5btu8kJxhMWrbXD4zEZ06O","7eoXzxrv9Gs62U989+zy9C","7e+venXlVEYKxo8GygzDzy","a4l2QBa0JCWKvfbvk1LZvL","c7Bvo3SFFE2b9sNq2nCpNj","cfAw7j1RxJHYLmfICDXzjf","d0n6H1E5dJGbTlL7CZs2Ix"],"scenes":{},"redirect":[],"deps":[],"packs":{"09d95e9b7":[104,54,106],"0b1bf3ba5":[105,87,111],"0e2f0e2a1":[67,107,110],"0fa310e9a":[0,1,2,3,4,5,6,7,8,9,10,11,12,13,14,15,16,17,18,19,20,21,22,23,24,25,26,27,28,29,30,31,32,33,34,35,36,37,38,39,40,41,42,43,44,45,46,47,48,49,50,51]},"name":"pbt_imgs","importBase":"import","nativeBase":"native","debug":false,"isZip":false,"encrypted":false,"versions":{"import":[52,"706dc",53,"adde4","09d95e9b7","dcb16","0b1bf3ba5","d6619","0e2f0e2a1","90933","0fa310e9a","d5cbd",55,"53348",56,"9641f",57,"26a6d",58,"92524",59,"ac6f2",60,"dada9",61,"84c37",62,"d627d",63,"a1108",64,"a783f",65,"45b6b",66,"a22aa",68,"f0424",69,"7f6d1",70,"19b9a",71,"a7537",72,"b6af5",73,"c046f",74,"67677",75,"fed43",76,"43087",108,"151c6",77,"8b41f",78,"1be92",79,"b37a3",80,"39ff0",81,"e924d",82,"b7490",109,"c75fe",83,"6058b",84,"39f98",85,"4a610",86,"de34e",88,"03993",89,"8d912",90,"1a566",91,"eca5f",112,"ae874",92,"00736",93,"14826",94,"6ad9a",95,"76236",96,"cda9d",97,"4394e",98,"fcd99",99,"028c3",100,"092ee",101,"0da06",102,"803a7",103,"e4bf4"],"native":[0,"57d6b",1,"03575",2,"0a86d",3,"2e086",4,"2ea82",5,"39e8c",6,"6c3a7",7,"99c3c",8,"9c680",9,"7f11d",10,"9c72f",11,"47716",12,"2b2f8",13,"dc792",14,"b2425",15,"a5006",16,"2e1d3",17,"3b400",18,"c14b9",19,"49199",20,"4e79a",21,"d6bd2",22,"497d7",23,"2b0b2",24,"e8a9d",25,"8cb97",26,"4d5b5",27,"d34f1",28,"24478",29,"74a42",30,"b3419",31,"900d6",32,"52b72",33,"b923b",34,"306ff",35,"3f4ef",36,"12ab0",37,"3a29b",38,"69084",39,"a9c8f",40,"72161",41,"421e2",42,"c3e38",43,"0635b",44,"bac57",45,"e1424",46,"d01a7",47,"4a6e5",48,"558f9",49,"def3e",50,"4a2ea",51,"752fd"]}}